{
    "general" : {
        "debug_enabled" : false,
        "default_alert_action" : "go",
        "default_radar_site" : "KLSX",
        "font_sizes" : [
            16,
            1,
            12
        ],
        "grid_width" : 1,
        "grid_height" : 1,
        "loop_delay" : 0,
        "loop_speed" : 1,
        "loop_time" : 1,
        "map_provider" : "maptiler",
        "mapbox_api_key" : "?",
        "maptiler_api_key" : "?",
        "update_notifications" : true
    },
    "maps" : [
        {
            "map_style" : "?",
            "radar_site" : "KLSX",
            "radar_product_group" : "L3",
            "radar_product" : "N0B"
        },
        {
            "map_style" : "?",
            "radar_site" : "KLSX",
            "radar_product_group" : "L3",
            "radar_product" : "N0G"
        },
        {
            "map_style" : "?",
            "radar_site" : "KLSX",
            "radar_product_group" : "L3",
            "radar_product" : "N0C"
        },
        {
            "map_style" : "?",
            "radar_site" : "KLSX",
            "radar_product_group" : "L3",
            "radar_product" : "N0X"
        }
    ],
    "palette" : {
        "BR" : "",
        "BV" : "",
        "SW" : "",
        "CC" : "",
        "ZDR" : "",
        "PHI2" : "",
        "DOD" : "",
        "DSD" : "",
        "ET" : "",
        "STP" : "",
        "OHP" : "",
        "STPIN" : "",
        "OHPIN" : "",
        "PHI3" : "",
        "SRV" : "",
        "VIL" : "",
        "???" : "",
        "FF-active" : "#00000000",
        "FF-inactive" : "#00000000",
        "MA-active" : "#00000000",
        "MA-inactive" : "#00000000",
        "SQ-active" : "#00000000",
        "SQ-inactive" : "#00000000",
        "SV-active" : "#00000000",
        "SV-inactive" : "#00000000",
        "TO-active" : "#00000000",
        "TO-inactive" : "#00000000"
    },
    "ui" : {
        "level2_products_expanded" : false,
        "level2_settings_expanded" : true,
        "level3_products_expanded" : true,
        "map_settings_expanded" : true,
        "timeline_expanded" : true
    }
}
